.gitignore
.gitignore-github
LICENSE
MANIFEST.in
Makefile
README.md
README.rst
benchmark.py
build.py
setup.py
tox.ini
siphash/__init__.py
siphash_cffi.egg-info/PKG-INFO
siphash_cffi.egg-info/SOURCES.txt
siphash_cffi.egg-info/dependency_links.txt
siphash_cffi.egg-info/requires.txt
siphash_cffi.egg-info/top_level.txt
sources/halfsiphash.c
sources/halfsiphash_variable.c
sources/siphash.c
sources/siphash_variable.c
tests/conftest.py
tests/test_cases.py
tests/test_functionality.py
tests/test_validation.py