Metadata-Version: 1.1
Name: siphash-cffi
Version: 0.1.4
Summary: Tested, performant SipHash bindings for Python 3 with support for double-output-size, half-word and variable-round variants.
Home-page: https://github.com/kpdemetriou/siphash-cffi
Author: Phil Demetriou
Author-email: inbox@philonas.net
License: BSD
Platform: UNKNOWN
Classifier: Development Status :: 4 - Beta
Classifier: Intended Audience :: Developers
Classifier: Intended Audience :: Science/Research
Classifier: Intended Audience :: System Administrators
Classifier: Intended Audience :: Telecommunications Industry
Classifier: License :: OSI Approved :: BSD License
Classifier: Programming Language :: C
Classifier: Programming Language :: Python :: 3
Classifier: Programming Language :: Python :: 3 :: Only
Classifier: Topic :: Security
Classifier: Topic :: Security :: Cryptography
Classifier: Topic :: Utilities
